CHANGELOG.md
eddysearch/__init__.py
eddysearch/objective.py
eddysearch/search/__init__.py
eddysearch/search/geneticsearch.py
eddysearch/search/gradient.py
eddysearch/search/population.py
eddysearch/search/randomsearch.py
eddysearch/strategy.py
eddysearch/visualization.py
eddysearch-0.3.0.dist-info/WHEEL
eddysearch-0.3.0.dist-info/METADATA
eddysearch-0.3.0.dist-info/RECORD
