Metadata-Version: 2.1
Name: eddysearch
Version: 0.3.0
Summary: 
Home-page: https://github.com/innvariant/eddy
License: MIT
Keywords: optimization,search strategy,evolutionary search,inference,training
Author: Julian Stier
Author-email: julian.stier@uni-passau.de
Requires-Python: >=3.7,<4.0
Classifier: License :: OSI Approved :: MIT License
Classifier: Programming Language :: Python :: 3
Classifier: Programming Language :: Python :: 3.7
Classifier: Programming Language :: Python :: 3.8
Requires-Dist: matplotlib (>=3.3,<4.0)
Requires-Dist: numpy (>=1.18,<2.0)
Project-URL: Documentation, https://github.com/innvariant/eddy
Project-URL: Repository, https://github.com/innvariant/eddy
